tdmgm/CycleThread.py
tdmgm/OnceThread.py
tdmgm/__init__.py
tdmgm/thread_utils.py
tdmgm-0.0.1.dist-info/METADATA
tdmgm-0.0.1.dist-info/WHEEL
tdmgm-0.0.1.dist-info/top_level.txt
tdmgm-0.0.1.dist-info/RECORD
