Metadata-Version: 2.4
Name: tdmgm
Version: 0.0.1
Summary: Python thread control, using ctypes to achieve forcibly terminating a thread even if it is still running.
Home-page: https://github.com/zaixia108/ThreadControl
Author: zaixia108
Author-email: zaixia108 <xvbowen2012@gmail.com>
Project-URL: Homepage, https://github.com/zaixia108/ThreadControl
Classifier: Programming Language :: Python :: 3
Classifier: License :: OSI Approved :: MIT License
Classifier: Operating System :: OS Independent
Requires-Python: >=3.8
Dynamic: author
Dynamic: home-page
Dynamic: requires-python
